bnot.py
bnot-1.1.dist-info/METADATA
bnot-1.1.dist-info/WHEEL
bnot-1.1.dist-info/licenses/LICENSE
bnot-1.1.dist-info/RECORD
