Metadata-Version: 2.1
Name: bnot
Version: 1.1
Summary: Bartek's Notation manager
Project-URL: Homepage, https://github.com/bwilk315/BarteksNotation
Project-URL: License, https://www.apache.org/licenses/LICENSE-2.0.txt
Author-email: bwilk315 <bwilk315@onet.pl>
License-File: LICENSE
Classifier: License :: OSI Approved :: Apache Software License
Classifier: Operating System :: OS Independent
Classifier: Programming Language :: Python :: 3
Requires-Python: >=3.5
